{"id": 658947661, "node_id": "MDg6QXJ0aWZhY3Q2NTg5NDc2NjE=", "name": "test-results", "size_in_bytes": 8404398, "url": "https://api.github.com/repos/KeYProject/key/actions/artifacts/658947661", "archive_download_url": "https://api.github.com/repos/KeYProject/key/actions/artifacts/658947661/zip", "expired": false, "created_at": "2023-04-21T13:05:28Z", "updated_at": "2023-04-21T13:05:29Z", "expires_at": "2023-07-20T11:52:00Z", "workflow_run": {"id": 4764463652, "repository_id": 580489837, "head_repository_id": 595176677, "head_branch": "weigl/jmlnames", "head_sha": "c0e264ff4dc5176c3967416c93938d8ddfb8a865"}}