{"id": 733019549, "node_id": "MDg6QXJ0aWZhY3Q3MzMwMTk1NDk=", "name": "test-results", "size_in_bytes": 30706726, "url": "https://api.github.com/repos/KeYProject/key/actions/artifacts/733019549", "archive_download_url": "https://api.github.com/repos/KeYProject/key/actions/artifacts/733019549/zip", "expired": false, "created_at": "2023-06-05T22:29:05Z", "updated_at": "2023-06-05T22:29:06Z", "expires_at": "2023-09-03T21:14:11Z", "workflow_run": {"id": 5181837472, "repository_id": 580489837, "head_repository_id": 580489837, "head_branch": "dependabot/gradle/org.sonarqube-4.2.0.3129", "head_sha": "8c6149af2c1f9dfb408dc28a97d4ea27703ca71d"}}