{"id": 625829390, "node_id": "MDg6QXJ0aWZhY3Q2MjU4MjkzOTA=", "name": "test-results", "size_in_bytes": 168915, "url": "https://api.github.com/repos/KeYProject/key/actions/artifacts/625829390", "archive_download_url": "https://api.github.com/repos/KeYProject/key/actions/artifacts/625829390/zip", "expired": false, "created_at": "2023-03-31T10:13:31Z", "updated_at": "2023-03-31T10:13:32Z", "expires_at": "2023-06-29T10:12:57Z", "workflow_run": {"id": 4573956368, "repository_id": 580489837, "head_repository_id": 595176677, "head_branch": "weigl/rmpcolparser", "head_sha": "d3b8ca9bb451be8e4a15dcf2fba142695212b3c2"}}