{"url": "https://api.github.com/repos/KeYProject/key/pulls/3012", "id": 1225065648, "node_id": "PR_kwDOIpmSbc5JBQSw", "html_url": "https://github.com/KeYProject/key/pull/3012", "diff_url": "https://github.com/KeYProject/key/pull/3012.diff", "patch_url": "https://github.com/KeYProject/key/pull/3012.patch", "issue_url": "https://api.github.com/repos/KeYProject/key/issues/3012", "number": 3012, "state": "closed", "locked": false, "title": "Proof tree view: Multiple small changes for readability", "user": {"login": "jwiesler", "id": 23399687, "node_id": "MDQ6VXNlcjIzMzk5Njg3", "avatar_url": "https://avatars.githubusercontent.com/u/23399687?v=4", "gravatar_id": "", "url": "https://api.github.com/users/jwiesler", "html_url": "https://github.com/jwiesler", "followers_url": "https://api.github.com/users/jwiesler/followers", "following_url": "https://api.github.com/users/jwiesler/following{/other_user}", "gists_url": "https://api.github.com/users/jwiesler/gists{/gist_id}", "starred_url": "https://api.github.com/users/jwiesler/starred{/owner}{/repo}", "subscriptions_url": "https://api.github.com/users/jwiesler/subscriptions", "organizations_url": "https://api.github.com/users/jwiesler/orgs", "repos_url": "https://api.github.com/users/jwiesler/repos", "events_url": "https://api.github.com/users/jwiesler/events{/privacy}", "received_events_url": "https://api.github.com/users/jwiesler/received_events", "type": "User", "site_admin": false}, "body": "I've digged these changes up from my main branch from over a year ago and made them cleaner.\r\n\r\n* Cleanup some of the code\r\n* Speed up ProofTreeSearchBar by caching the search strings (Makes a huge difference for large proofs)\r\n* Fix example dialog loading previously hidden example on double-click on a folder\r\n\r\n### Elide long rule app names and move them to the tooltip\r\n\r\n![grafik](https://user-images.githubusercontent.com/23399687/216086114-a5e442db-c30d-4e66-9b28-a192ab4f79b7.png)\r\n\r\n### Normalize whitespace in rule names\r\nAfter: ![grafik](https://user-images.githubusercontent.com/23399687/216086358-e2badf5a-f3f6-424e-b867-eaba872f0470.png)\r\n\r\nBefore: ![grafik](https://user-images.githubusercontent.com/23399687/216086390-50dad39f-1c74-4300-bab2-d7b6f2c73fa4.png)\r\n\r\n### Move applied on term of OSS nodes to the tooltip\r\n\r\nAfter: \r\n![grafik](https://user-images.githubusercontent.com/23399687/216086641-7e7ec221-0130-4edd-aa53-dfa0104e6132.png)\r\n\r\nBefore: \r\n![grafik](https://user-images.githubusercontent.com/23399687/216086660-d1521c1b-bd57-404a-a297-45a4afb4f7de.png)\r\n\r\n", "created_at": "2023-02-01T15:29:54Z", "updated_at": "2023-03-10T12:18:12Z", "closed_at": "2023-02-11T15:29:37Z", "merged_at": "2023-02-11T15:29:37Z", "merge_commit_sha": "87ceb1cd6f965beeb584b66d372ee5eb09cf4571", "assignee": {"login": "jwiesler", "id": 23399687, "node_id": "MDQ6VXNlcjIzMzk5Njg3", "avatar_url": "https://avatars.githubusercontent.com/u/23399687?v=4", "gravatar_id": "", "url": "https://api.github.com/users/jwiesler", "html_url": "https://github.com/jwiesler", "followers_url": "https://api.github.com/users/jwiesler/followers", "following_url": "https://api.github.com/users/jwiesler/following{/other_user}", "gists_url": "https://api.github.com/users/jwiesler/gists{/gist_id}", "starred_url": "https://api.github.com/users/jwiesler/starred{/owner}{/repo}", "subscriptions_url": "https://api.github.com/users/jwiesler/subscriptions", "organizations_url": "https://api.github.com/users/jwiesler/orgs", "repos_url": "https://api.github.com/users/jwiesler/repos", "events_url": "https://api.github.com/users/jwiesler/events{/privacy}", "received_events_url": "https://api.github.com/users/jwiesler/received_events", "type": "User", "site_admin": false}, "assignees": [{"login": "jwiesler", "id": 23399687, "node_id": "MDQ6VXNlcjIzMzk5Njg3", "avatar_url": "https://avatars.githubusercontent.com/u/23399687?v=4", "gravatar_id": "", "url": "https://api.github.com/users/jwiesler", "html_url": "https://github.com/jwiesler", "followers_url": "https://api.github.com/users/jwiesler/followers", "following_url": "https://api.github.com/users/jwiesler/following{/other_user}", "gists_url": "https://api.github.com/users/jwiesler/gists{/gist_id}", "starred_url": "https://api.github.com/users/jwiesler/starred{/owner}{/repo}", "subscriptions_url": "https://api.github.com/users/jwiesler/subscriptions", "organizations_url": "https://api.github.com/users/jwiesler/orgs", "repos_url": "https://api.github.com/users/jwiesler/repos", "events_url": "https://api.github.com/users/jwiesler/events{/privacy}", "received_events_url": "https://api.github.com/users/jwiesler/received_events", "type": "User", "site_admin": false}], "requested_reviewers": [], "requested_teams": [], "labels": [], "milestone": null, "draft": false, "commits_url": "https://api.github.com/repos/KeYProject/key/pulls/3012/commits", "review_comments_url": "https://api.github.com/repos/KeYProject/key/pulls/3012/comments", "review_comment_url": "https://api.github.com/repos/KeYProject/key/pulls/comments{/number}", "comments_url": "https://api.github.com/repos/KeYProject/key/issues/3012/comments", "statuses_url": "https://api.github.com/repos/KeYProject/key/statuses/ab03a6aecafc0a95cd276eacbd880c6abf184d6c", "head": {"label": "jwiesler:prooftree", "ref": "prooftree", "sha": "ab03a6aecafc0a95cd276eacbd880c6abf184d6c", "user": {"login": "jwiesler", "id": 23399687, "node_id": "MDQ6VXNlcjIzMzk5Njg3", "avatar_url": "https://avatars.githubusercontent.com/u/23399687?v=4", "gravatar_id": "", "url": "https://api.github.com/users/jwiesler", "html_url": "https://github.com/jwiesler", "followers_url": "https://api.github.com/users/jwiesler/followers", "following_url": "https://api.github.com/users/jwiesler/following{/other_user}", "gists_url": "https://api.github.com/users/jwiesler/gists{/gist_id}", "starred_url": "https://api.github.com/users/jwiesler/starred{/owner}{/repo}", "subscriptions_url": "https://api.github.com/users/jwiesler/subscriptions", "organizations_url": "https://api.github.com/users/jwiesler/orgs", "repos_url": "https://api.github.com/users/jwiesler/repos", "events_url": "https://api.github.com/users/jwiesler/events{/privacy}", "received_events_url": "https://api.github.com/users/jwiesler/received_events", "type": "User", "site_admin": false}, "repo": {"id": 596143354, "node_id": "R_kgDOI4hs-g", "name": "key", "full_name": "jwiesler/key", "private": false, "owner": {"login": "jwiesler", "id": 23399687, "node_id": "MDQ6VXNlcjIzMzk5Njg3", "avatar_url": "https://avatars.githubusercontent.com/u/23399687?v=4", "gravatar_id": "", "url": "https://api.github.com/users/jwiesler", "html_url": "https://github.com/jwiesler", "followers_url": "https://api.github.com/users/jwiesler/followers", "following_url": "https://api.github.com/users/jwiesler/following{/other_user}", "gists_url": "https://api.github.com/users/jwiesler/gists{/gist_id}", "starred_url": "https://api.github.com/users/jwiesler/starred{/owner}{/repo}", "subscriptions_url": "https://api.github.com/users/jwiesler/subscriptions", "organizations_url": "https://api.github.com/users/jwiesler/orgs", "repos_url": "https://api.github.com/users/jwiesler/repos", "events_url": "https://api.github.com/users/jwiesler/events{/privacy}", "received_events_url": "https://api.github.com/users/jwiesler/received_events", "type": "User", "site_admin": false}, "html_url": "https://github.com/jwiesler/key", "description": "KeY Theorem Prover for Deductive Java Verification", "fork": true, "url": "https://api.github.com/repos/jwiesler/key", "forks_url": "https://api.github.com/repos/jwiesler/key/forks", "keys_url": "https://api.github.com/repos/jwiesler/key/keys{/key_id}", "collaborators_url": "https://api.github.com/repos/jwiesler/key/collaborators{/collaborator}", "teams_url": "https://api.github.com/repos/jwiesler/key/teams", "hooks_url": "https://api.github.com/repos/jwiesler/key/hooks", "issue_events_url": "https://api.github.com/repos/jwiesler/key/issues/events{/number}", "events_url": "https://api.github.com/repos/jwiesler/key/events", "assignees_url": "https://api.github.com/repos/jwiesler/key/assignees{/user}", "branches_url": "https://api.github.com/repos/jwiesler/key/branches{/branch}", "tags_url": "https://api.github.com/repos/jwiesler/key/tags", "blobs_url": "https://api.github.com/repos/jwiesler/key/git/blobs{/sha}", "git_tags_url": "https://api.github.com/repos/jwiesler/key/git/tags{/sha}", "git_refs_url": "https://api.github.com/repos/jwiesler/key/git/refs{/sha}", "trees_url": "https://api.github.com/repos/jwiesler/key/git/trees{/sha}", "statuses_url": "https://api.github.com/repos/jwiesler/key/statuses/{sha}", "languages_url": "https://api.github.com/repos/jwiesler/key/languages", "stargazers_url": "https://api.github.com/repos/jwiesler/key/stargazers", "contributors_url": "https://api.github.com/repos/jwiesler/key/contributors", "subscribers_url": "https://api.github.com/repos/jwiesler/key/subscribers", "subscription_url": "https://api.github.com/repos/jwiesler/key/subscription", "commits_url": "https://api.github.com/repos/jwiesler/key/commits{/sha}", "git_commits_url": "https://api.github.com/repos/jwiesler/key/git/commits{/sha}", "comments_url": "https://api.github.com/repos/jwiesler/key/comments{/number}", "issue_comment_url": "https://api.github.com/repos/jwiesler/key/issues/comments{/number}", "contents_url": "https://api.github.com/repos/jwiesler/key/contents/{+path}", "compare_url": "https://api.github.com/repos/jwiesler/key/compare/{base}...{head}", "merges_url": "https://api.github.com/repos/jwiesler/key/merges", "archive_url": "https://api.github.com/repos/jwiesler/key/{archive_format}{/ref}", "downloads_url": "https://api.github.com/repos/jwiesler/key/downloads", "issues_url": "https://api.github.com/repos/jwiesler/key/issues{/number}", "pulls_url": "https://api.github.com/repos/jwiesler/key/pulls{/number}", "milestones_url": "https://api.github.com/repos/jwiesler/key/milestones{/number}", "notifications_url": "https://api.github.com/repos/jwiesler/key/notifications{?since,all,participating}", "labels_url": "https://api.github.com/repos/jwiesler/key/labels{/name}", "releases_url": "https://api.github.com/repos/jwiesler/key/releases{/id}", "deployments_url": "https://api.github.com/repos/jwiesler/key/deployments", "created_at": "2023-02-01T15:00:57Z", "updated_at": "2023-02-01T10:30:31Z", "pushed_at": "2023-04-07T20:15:49Z", "git_url": "git://github.com/jwiesler/key.git", "ssh_url": "git@github.com:jwiesler/key.git", "clone_url": "https://github.com/jwiesler/key.git", "svn_url": "https://github.com/jwiesler/key", "homepage": "https://key-project.org", "size": 525172, "stargazers_count": 0, "watchers_count": 0, "language": null, "has_issues": false, "has_projects": true, "has_downloads": true, "has_wiki": true, "has_pages": false, "has_discussions": false, "forks_count": 0, "mirror_url": null, "archived": false, "disabled": false, "open_issues_count": 1, "license": {"key": "other", "name": "Other", "spdx_id": "NOASSERTION", "url": null, "node_id": "MDc6TGljZW5zZTA="}, "allow_forking": true, "is_template": false, "web_commit_signoff_required": false, "topics": [], "visibility": "public", "forks": 0, "open_issues": 1, "watchers": 0, "default_branch": "main"}}, "base": {"label": "KeYProject:main", "ref": "main", "sha": "637b0e037e7b5a7b9a61d3db99c87fb09598c0bd", "user": {"login": "KeYProject", "id": 18749969, "node_id": "MDEyOk9yZ2FuaXphdGlvbjE4NzQ5OTY5", "avatar_url": "https://avatars.githubusercontent.com/u/18749969?v=4", "gravatar_id": "", "url": "https://api.github.com/users/KeYProject", "html_url": "https://github.com/KeYProject", "followers_url": "https://api.github.com/users/KeYProject/followers", "following_url": "https://api.github.com/users/KeYProject/following{/other_user}", "gists_url": "https://api.github.com/users/KeYProject/gists{/gist_id}", "starred_url": "https://api.github.com/users/KeYProject/starred{/owner}{/repo}", "subscriptions_url": "https://api.github.com/users/KeYProject/subscriptions", "organizations_url": "https://api.github.com/users/KeYProject/orgs", "repos_url": "https://api.github.com/users/KeYProject/repos", "events_url": "https://api.github.com/users/KeYProject/events{/privacy}", "received_events_url": "https://api.github.com/users/KeYProject/received_events", "type": "Organization", "site_admin": false}, "repo": {"id": 580489837, "node_id": "R_kgDOIpmSbQ", "name": "key", "full_name": "KeYProject/key", "private": false, "owner": {"login": "KeYProject", "id": 18749969, "node_id": "MDEyOk9yZ2FuaXphdGlvbjE4NzQ5OTY5", "avatar_url": "https://avatars.githubusercontent.com/u/18749969?v=4", "gravatar_id": "", "url": "https://api.github.com/users/KeYProject", "html_url": "https://github.com/KeYProject", "followers_url": "https://api.github.com/users/KeYProject/followers", "following_url": "https://api.github.com/users/KeYProject/following{/other_user}", "gists_url": "https://api.github.com/users/KeYProject/gists{/gist_id}", "starred_url": "https://api.github.com/users/KeYProject/starred{/owner}{/repo}", "subscriptions_url": "https://api.github.com/users/KeYProject/subscriptions", "organizations_url": "https://api.github.com/users/KeYProject/orgs", "repos_url": "https://api.github.com/users/KeYProject/repos", "events_url": "https://api.github.com/users/KeYProject/events{/privacy}", "received_events_url": "https://api.github.com/users/KeYProject/received_events", "type": "Organization", "site_admin": false}, "html_url": "https://github.com/KeYProject/key", "description": "KeY Theorem Prover for Deductive Java Verification", "fork": false, "url": "https://api.github.com/repos/KeYProject/key", "forks_url": "https://api.github.com/repos/KeYProject/key/forks", "keys_url": "https://api.github.com/repos/KeYProject/key/keys{/key_id}", "collaborators_url": "https://api.github.com/repos/KeYProject/key/collaborators{/collaborator}", "teams_url": "https://api.github.com/repos/KeYProject/key/teams", "hooks_url": "https://api.github.com/repos/KeYProject/key/hooks", "issue_events_url": "https://api.github.com/repos/KeYProject/key/issues/events{/number}", "events_url": "https://api.github.com/repos/KeYProject/key/events", "assignees_url": "https://api.github.com/repos/KeYProject/key/assignees{/user}", "branches_url": "https://api.github.com/repos/KeYProject/key/branches{/branch}", "tags_url": "https://api.github.com/repos/KeYProject/key/tags", "blobs_url": "https://api.github.com/repos/KeYProject/key/git/blobs{/sha}", "git_tags_url": "https://api.github.com/repos/KeYProject/key/git/tags{/sha}", "git_refs_url": "https://api.github.com/repos/KeYProject/key/git/refs{/sha}", "trees_url": "https://api.github.com/repos/KeYProject/key/git/trees{/sha}", "statuses_url": "https://api.github.com/repos/KeYProject/key/statuses/{sha}", "languages_url": "https://api.github.com/repos/KeYProject/key/languages", "stargazers_url": "https://api.github.com/repos/KeYProject/key/stargazers", "contributors_url": "https://api.github.com/repos/KeYProject/key/contributors", "subscribers_url": "https://api.github.com/repos/KeYProject/key/subscribers", "subscription_url": "https://api.github.com/repos/KeYProject/key/subscription", "commits_url": "https://api.github.com/repos/KeYProject/key/commits{/sha}", "git_commits_url": "https://api.github.com/repos/KeYProject/key/git/commits{/sha}", "comments_url": "https://api.github.com/repos/KeYProject/key/comments{/number}", "issue_comment_url": "https://api.github.com/repos/KeYProject/key/issues/comments{/number}", "contents_url": "https://api.github.com/repos/KeYProject/key/contents/{+path}", "compare_url": "https://api.github.com/repos/KeYProject/key/compare/{base}...{head}", "merges_url": "https://api.github.com/repos/KeYProject/key/merges", "archive_url": "https://api.github.com/repos/KeYProject/key/{archive_format}{/ref}", "downloads_url": "https://api.github.com/repos/KeYProject/key/downloads", "issues_url": "https://api.github.com/repos/KeYProject/key/issues{/number}", "pulls_url": "https://api.github.com/repos/KeYProject/key/pulls{/number}", "milestones_url": "https://api.github.com/repos/KeYProject/key/milestones{/number}", "notifications_url": "https://api.github.com/repos/KeYProject/key/notifications{?since,all,participating}", "labels_url": "https://api.github.com/repos/KeYProject/key/labels{/name}", "releases_url": "https://api.github.com/repos/KeYProject/key/releases{/id}", "deployments_url": "https://api.github.com/repos/KeYProject/key/deployments", "created_at": "2022-12-20T17:32:07Z", "updated_at": "2023-03-22T22:02:23Z", "pushed_at": "2023-04-08T05:43:01Z", "git_url": "git://github.com/KeYProject/key.git", "ssh_url": "git@github.com:KeYProject/key.git", "clone_url": "https://github.com/KeYProject/key.git", "svn_url": "https://github.com/KeYProject/key", "homepage": "https://key-project.org", "size": 143100, "stargazers_count": 13, "watchers_count": 13, "language": "Java", "has_issues": true, "has_projects": true, "has_downloads": true, "has_wiki": true, "has_pages": false, "has_discussions": true, "forks_count": 7, "mirror_url": null, "archived": false, "disabled": false, "open_issues_count": 356, "license": {"key": "other", "name": "Other", "spdx_id": "NOASSERTION", "url": null, "node_id": "MDc6TGljZW5zZTA="}, "allow_forking": true, "is_template": false, "web_commit_signoff_required": false, "topics": ["formal-verification", "key", "smt-solver", "static-analysis"], "visibility": "public", "forks": 7, "open_issues": 356, "watchers": 13, "default_branch": "main"}}, "_links": {"self": {"href": "https://api.github.com/repos/KeYProject/key/pulls/3012"}, "html": {"href": "https://github.com/KeYProject/key/pull/3012"}, "issue": {"href": "https://api.github.com/repos/KeYProject/key/issues/3012"}, "comments": {"href": "https://api.github.com/repos/KeYProject/key/issues/3012/comments"}, "review_comments": {"href": "https://api.github.com/repos/KeYProject/key/pulls/3012/comments"}, "review_comment": {"href": "https://api.github.com/repos/KeYProject/key/pulls/comments{/number}"}, "commits": {"href": "https://api.github.com/repos/KeYProject/key/pulls/3012/commits"}, "statuses": {"href": "https://api.github.com/repos/KeYProject/key/statuses/ab03a6aecafc0a95cd276eacbd880c6abf184d6c"}}, "author_association": "CONTRIBUTOR", "auto_merge": {"enabled_by": {"login": "wadoon", "id": 104259, "node_id": "MDQ6VXNlcjEwNDI1OQ==", "avatar_url": "https://avatars.githubusercontent.com/u/104259?v=4", "gravatar_id": "", "url": "https://api.github.com/users/wadoon", "html_url": "https://github.com/wadoon", "followers_url": "https://api.github.com/users/wadoon/followers", "following_url": "https://api.github.com/users/wadoon/following{/other_user}", "gists_url": "https://api.github.com/users/wadoon/gists{/gist_id}", "starred_url": "https://api.github.com/users/wadoon/starred{/owner}{/repo}", "subscriptions_url": "https://api.github.com/users/wadoon/subscriptions", "organizations_url": "https://api.github.com/users/wadoon/orgs", "repos_url": "https://api.github.com/users/wadoon/repos", "events_url": "https://api.github.com/users/wadoon/events{/privacy}", "received_events_url": "https://api.github.com/users/wadoon/received_events", "type": "User", "site_admin": false}, "merge_method": "merge", "commit_title": "Proof tree view: Multiple small changes for readability (#3012)", "commit_message": "I've digged these changes up from my main branch from over a year ago\r\nand made them cleaner.\r\n\r\n* Cleanup some of the code\r\n* Speed up ProofTreeSearchBar by caching the search strings (Makes a\r\nhuge difference for large proofs)\r\n* Fix example dialog loading previously hidden example on double-click\r\non a folder\r\n\r\n### Elide long rule app names and move them to the tooltip\r\n\r\n\r\n![grafik](https://user-images.githubusercontent.com/23399687/216086114-a5e442db-c30d-4e66-9b28-a192ab4f79b7.png)\r\n\r\n### Normalize whitespace in rule names\r\nAfter:\r\n![grafik](https://user-images.githubusercontent.com/23399687/216086358-e2badf5a-f3f6-424e-b867-eaba872f0470.png)\r\n\r\nBefore:\r\n![grafik](https://user-images.githubusercontent.com/23399687/216086390-50dad39f-1c74-4300-bab2-d7b6f2c73fa4.png)\r\n\r\n### Move applied on term of OSS nodes to the tooltip\r\n\r\nAfter: \r\n\r\n![grafik](https://user-images.githubusercontent.com/23399687/216086641-7e7ec221-0130-4edd-aa53-dfa0104e6132.png)\r\n\r\nBefore: \r\n\r\n![grafik](https://user-images.githubusercontent.com/23399687/216086660-d1521c1b-bd57-404a-a297-45a4afb4f7de.png)"}, "active_lock_reason": null}